[
  {
    "text": "welcome to office hours with propy this",
    "start": 0.04,
    "duration": 2.92
  },
  {
    "text": "is the part of the show where we answer",
    "start": 1.76,
    "duration": 2.519
  },
  {
    "text": "your questions about business B Tech",
    "start": 2.96,
    "duration": 2.919
  },
  {
    "text": "entrepreneurship and whatever else is on",
    "start": 4.279,
    "duration": 3.281
  },
  {
    "text": "your mind if you'd like to submit a",
    "start": 5.879,
    "duration": 3.84
  },
  {
    "text": "question please email a voice recording",
    "start": 7.56,
    "duration": 4.4
  },
  {
    "text": "to office hours atpr media.com again",
    "start": 9.719,
    "duration": 4.481
  },
  {
    "text": "that's office hours propy",
    "start": 11.96,
    "duration": 4.92
  },
  {
    "text": "media.com question number",
    "start": 14.2,
    "duration": 6.68
  },
  {
    "text": "one hi Prof G and Ed love the show I was",
    "start": 16.88,
    "duration": 6.479
  },
  {
    "text": "wondering if the same demographic Trends",
    "start": 20.88,
    "duration": 4.52
  },
  {
    "text": "affecting higher ed will affect",
    "start": 23.359,
    "duration": 4.32
  },
  {
    "text": "companies like Disney who rely upon a",
    "start": 25.4,
    "duration": 4.76
  },
  {
    "text": "younger demographic for the streaming",
    "start": 27.679,
    "duration": 5.361
  },
  {
    "text": "content venues and other products in",
    "start": 30.16,
    "duration": 5.68
  },
  {
    "text": "other words with fewer babies being born",
    "start": 33.04,
    "duration": 4.96
  },
  {
    "text": "and as people age they will drop their",
    "start": 35.84,
    "duration": 4.84
  },
  {
    "text": "Disney subscriptions forcing Disney to",
    "start": 38.0,
    "duration": 5.84
  },
  {
    "text": "find new subscribers from a smaller pool",
    "start": 40.68,
    "duration": 5.039
  },
  {
    "text": "what other companies might face this",
    "start": 43.84,
    "duration": 4.52
  },
  {
    "text": "demographic challenge it's a really",
    "start": 45.719,
    "duration": 4.041
  },
  {
    "text": "interesting question I think about this",
    "start": 48.36,
    "duration": 3.08
  },
  {
    "text": "through the lens of I have a son who",
    "start": 49.76,
    "duration": 3.92
  },
  {
    "text": "will be applying to college and actually",
    "start": 51.44,
    "duration": 4.08
  },
  {
    "text": "for the first time in my you know the",
    "start": 53.68,
    "duration": 3.92
  },
  {
    "text": "demographics are on his side fewer boys",
    "start": 55.52,
    "duration": 3.679
  },
  {
    "text": "are applying to a college and just fewer",
    "start": 57.6,
    "duration": 3.599
  },
  {
    "text": "people are applying to College although",
    "start": 59.199,
    "duration": 3.721
  },
  {
    "text": "what's against him is you know because",
    "start": 61.199,
    "duration": 3.561
  },
  {
    "text": "I'm a narcissist and want him to go to a",
    "start": 62.92,
    "duration": 4.08
  },
  {
    "text": "quote unquote Prestige or elite school",
    "start": 64.76,
    "duration": 4.8
  },
  {
    "text": "is that true you know it's sort of true",
    "start": 67.0,
    "duration": 4.08
  },
  {
    "text": "I kind of come to the conclusion I just",
    "start": 69.56,
    "duration": 4.919
  },
  {
    "text": "want to be happy but anyways uh what you",
    "start": 71.08,
    "duration": 6.399
  },
  {
    "text": "see is a crowding effect into the best",
    "start": 74.479,
    "duration": 4.761
  },
  {
    "text": "universities but on the whole you're",
    "start": 77.479,
    "duration": 4.201
  },
  {
    "text": "going to see tier 2 universities go out",
    "start": 79.24,
    "duration": 4.28
  },
  {
    "text": "of business like no tomorrow people",
    "start": 81.68,
    "duration": 3.88
  },
  {
    "text": "under the age of 18 represent roughly",
    "start": 83.52,
    "duration": 4.2
  },
  {
    "text": "21% of the total American population",
    "start": 85.56,
    "duration": 5.879
  },
  {
    "text": "down from 36% in the 60s Jesus Christ",
    "start": 87.72,
    "duration": 5.679
  },
  {
    "text": "you want to worry about social security",
    "start": 91.439,
    "duration": 3.161
  },
  {
    "text": "who's going to pay for this goddamn",
    "start": 93.399,
    "duration": 2.4
  },
  {
    "text": "thing it's young people paying for it",
    "start": 94.6,
    "duration": 2.96
  },
  {
    "text": "right now and there used to be like you",
    "start": 95.799,
    "duration": 4.481
  },
  {
    "text": "know 12 to1 uh working age people the",
    "start": 97.56,
    "duration": 4.32
  },
  {
    "text": "seniors now it's something like 3 to1 in",
    "start": 100.28,
    "duration": 3.119
  },
  {
    "text": "the next 20 years it's projected that",
    "start": 101.88,
    "duration": 3.0
  },
  {
    "text": "American share of children will fall by",
    "start": 103.399,
    "duration": 3.921
  },
  {
    "text": "an additional three percentage points",
    "start": 104.88,
    "duration": 4.559
  },
  {
    "text": "the Census Bureau estimates that by 2060",
    "start": 107.32,
    "duration": 3.839
  },
  {
    "text": "America will out over 8 million children",
    "start": 109.439,
    "duration": 4.04
  },
  {
    "text": "in comparison they estimate Americans",
    "start": 111.159,
    "duration": 5.201
  },
  {
    "text": "over the age of 65 will increase by",
    "start": 113.479,
    "duration": 6.6
  },
  {
    "text": "about 37 million okay get this 8 million",
    "start": 116.36,
    "duration": 5.679
  },
  {
    "text": "kids 37 million more old people the",
    "start": 120.079,
    "duration": 3.481
  },
  {
    "text": "falling birth rate will likely have",
    "start": 122.039,
    "duration": 3.44
  },
  {
    "text": "significant impacts on business",
    "start": 123.56,
    "duration": 3.839
  },
  {
    "text": "including Baby product manufacturers",
    "start": 125.479,
    "duration": 3.521
  },
  {
    "text": "childcare services and education",
    "start": 127.399,
    "duration": 3.64
  },
  {
    "text": "providers additionally there'll be an",
    "start": 129.0,
    "duration": 3.56
  },
  {
    "text": "enormous increase in demand for products",
    "start": 131.039,
    "duration": 2.92
  },
  {
    "text": "and services aimed at the elderly",
    "start": 132.56,
    "duration": 2.959
  },
  {
    "text": "population including senior care and",
    "start": 133.959,
    "duration": 4.161
  },
  {
    "text": "retirement communities yeah no doubt uh",
    "start": 135.519,
    "duration": 4.961
  },
  {
    "text": "some of the companies catering to kids",
    "start": 138.12,
    "duration": 4.839
  },
  {
    "text": "will suffer but coming like Disney I",
    "start": 140.48,
    "duration": 4.399
  },
  {
    "text": "think they're fine because one it's so",
    "start": 142.959,
    "duration": 4.041
  },
  {
    "text": " crowded as it is and if it's",
    "start": 144.879,
    "duration": 4.801
  },
  {
    "text": "become a ride of Passage people you know",
    "start": 147.0,
    "duration": 3.959
  },
  {
    "text": "you you're likely going to have child",
    "start": 149.68,
    "duration": 2.96
  },
  {
    "text": "services called on you if you don't take",
    "start": 150.959,
    "duration": 3.28
  },
  {
    "text": "your kids to Disney for what is the",
    "start": 152.64,
    "duration": 3.679
  },
  {
    "text": "seventh circle of hell for a weekend of",
    "start": 154.239,
    "duration": 4.72
  },
  {
    "text": "overpriced hotels and shitty food and",
    "start": 156.319,
    "duration": 4.801
  },
  {
    "text": "two-hour lines to get on the Avatar ride",
    "start": 158.959,
    "duration": 3.441
  },
  {
    "text": "I think Disney's going to be fine",
    "start": 161.12,
    "duration": 2.6
  },
  {
    "text": "because there's a flight to Quality and",
    "start": 162.4,
    "duration": 3.6
  },
  {
    "text": "people will stop you know go one level",
    "start": 163.72,
    "duration": 4.439
  },
  {
    "text": "down Six Flags Magic Mountain or Bush",
    "start": 166.0,
    "duration": 4.44
  },
  {
    "text": "Gardens or whatever it is now I think",
    "start": 168.159,
    "duration": 4.201
  },
  {
    "text": "they'll suffer but I think what people",
    "start": 170.44,
    "duration": 3.64
  },
  {
    "text": "will do is end up spending more money",
    "start": 172.36,
    "duration": 2.959
  },
  {
    "text": "across fewer there's going to be a",
    "start": 174.08,
    "duration": 2.76
  },
  {
    "text": "flight to Quality just the same way that",
    "start": 175.319,
    "duration": 3.881
  },
  {
    "text": "despite there being fewer young people",
    "start": 176.84,
    "duration": 3.96
  },
  {
    "text": "the elite col colleges are booming",
    "start": 179.2,
    "duration": 2.84
  },
  {
    "text": "because there's a kind of a rush to",
    "start": 180.8,
    "duration": 2.64
  },
  {
    "text": "Quality and they create this illusion of",
    "start": 182.04,
    "duration": 3.839
  },
  {
    "text": "scarcity they get more Capital trade at",
    "start": 183.44,
    "duration": 4.6
  },
  {
    "text": "a higher multiple reinvest in the new",
    "start": 185.879,
    "duration": 3.961
  },
  {
    "text": "you know the new Star Wars land or Rogue",
    "start": 188.04,
    "duration": 3.6
  },
  {
    "text": "n or whatever it is and they kind of",
    "start": 189.84,
    "duration": 4.2
  },
  {
    "text": "pull ahead uh from the competition by",
    "start": 191.64,
    "duration": 4.04
  },
  {
    "text": "the way Disney for kids and Universal",
    "start": 194.04,
    "duration": 3.199
  },
  {
    "text": "for the teenagers is what I've",
    "start": 195.68,
    "duration": 4.16
  },
  {
    "text": "discovered as I've gotten older the",
    "start": 197.239,
    "duration": 4.321
  },
  {
    "text": "problems here are bigger than consumer",
    "start": 199.84,
    "duration": 3.8
  },
  {
    "text": "companies and that is now about 40% of",
    "start": 201.56,
    "duration": 5.16
  },
  {
    "text": "our budget goes to uh Services",
    "start": 203.64,
    "duration": 5.799
  },
  {
    "text": "Medicare um social security for people",
    "start": 206.72,
    "duration": 4.76
  },
  {
    "text": "over the age of 65 and it's about to go",
    "start": 209.439,
    "duration": 4.0
  },
  {
    "text": "over 50% because we have an aging",
    "start": 211.48,
    "duration": 3.64
  },
  {
    "text": "population and we don't means test and",
    "start": 213.439,
    "duration": 3.961
  },
  {
    "text": "they vote so we just cram more and more",
    "start": 215.12,
    "duration": 4.039
  },
  {
    "text": "wealth uh old people have figured out",
    "start": 217.4,
    "duration": 3.88
  },
  {
    "text": "they can vote themselves more money it",
    "start": 219.159,
    "duration": 3.601
  },
  {
    "text": "is ridiculous that we don't have means",
    "start": 221.28,
    "duration": 3.0
  },
  {
    "text": "testing for Social Security it is",
    "start": 222.76,
    "duration": 3.96
  },
  {
    "text": "ridiculous that the age hasn't been",
    "start": 224.28,
    "duration": 4.84
  },
  {
    "text": "dramatically elevated 65 people aren't",
    "start": 226.72,
    "duration": 4.12
  },
  {
    "text": "even getting elected to the Senate",
    "start": 229.12,
    "duration": 3.0
  },
  {
    "text": "they're like a young they're like the",
    "start": 230.84,
    "duration": 3.64
  },
  {
    "text": "hot young thing when they show up to the",
    "start": 232.12,
    "duration": 5.0
  },
  {
    "text": "Senate at 65 we absolutely need to",
    "start": 234.48,
    "duration": 4.8
  },
  {
    "text": "address this not only this aging but the",
    "start": 237.12,
    "duration": 3.92
  },
  {
    "text": "fact that we continue to cram more money",
    "start": 239.28,
    "duration": 4.4
  },
  {
    "text": "into the pockets of the old people I",
    "start": 241.04,
    "duration": 4.88
  },
  {
    "text": "believe you could reverse engineer all",
    "start": 243.68,
    "duration": 3.72
  },
  {
    "text": "of the biggest issues in our society",
    "start": 245.92,
    "duration": 4.2
  },
  {
    "text": "income inequality polarization extremism",
    "start": 247.4,
    "duration": 5.0
  },
  {
    "text": "to One Thing One stat and that is for",
    "start": 250.12,
    "duration": 3.92
  },
  {
    "text": "the first time in our nation's history a",
    "start": 252.4,
    "duration": 3.08
  },
  {
    "text": "30-year-old isn't doing as well as his",
    "start": 254.04,
    "duration": 3.159
  },
  {
    "text": "or her parents were at 30 that is a",
    "start": 255.48,
    "duration": 3.12
  },
  {
    "text": "breakdown on the social compact it",
    "start": 257.199,
    "duration": 3.361
  },
  {
    "text": "doesn't doesn't mean a thing",
    "start": 258.6,
    "duration": 3.56
  },
  {
    "text": "that the S&P is touching new highs it",
    "start": 260.56,
    "duration": 4.04
  },
  {
    "text": "doesn't mean anything with GDP growth is",
    "start": 262.16,
    "duration": 5.12
  },
  {
    "text": "if your kids aren't doing as well as you",
    "start": 264.6,
    "duration": 5.36
  },
  {
    "text": "uh so this this canotes a bigger problem",
    "start": 267.28,
    "duration": 4.0
  },
  {
    "text": "specifically not only what it means for",
    "start": 269.96,
    "duration": 4.32
  },
  {
    "text": "Consumer brands with a population dir",
    "start": 271.28,
    "duration": 4.84
  },
  {
    "text": "but what it means for our society when",
    "start": 274.28,
    "duration": 3.199
  },
  {
    "text": "people no longer have the money or the",
    "start": 276.12,
    "duration": 3.68
  },
  {
    "text": "confidence to have their own children",
    "start": 277.479,
    "duration": 4.801
  },
  {
    "text": "thanks for the question question number",
    "start": 279.8,
    "duration": 5.119
  },
  {
    "text": "two hey Scott this is Sean calling from",
    "start": 282.28,
    "duration": 4.759
  },
  {
    "text": "the Sunshine State of Florida I'm a huge",
    "start": 284.919,
    "duration": 4.12
  },
  {
    "text": "fan of you and all of your shows while",
    "start": 287.039,
    "duration": 3.44
  },
  {
    "text": "I've heard you speak about many many",
    "start": 289.039,
    "duration": 3.121
  },
  {
    "text": "things and this show is called office",
    "start": 290.479,
    "duration": 3.56
  },
  {
    "text": "hours I've somehow missed you discuss",
    "start": 292.16,
    "duration": 4.36
  },
  {
    "text": "your life working in Academia I began",
    "start": 294.039,
    "duration": 3.961
  },
  {
    "text": "adjunct teaching on the side while",
    "start": 296.52,
    "duration": 2.72
  },
  {
    "text": "working in the clinical world of",
    "start": 298.0,
    "duration": 2.199
  },
  {
    "text": "healthcare",
    "start": 299.24,
    "duration": 2.72
  },
  {
    "text": "I realized I absolutely love teaching",
    "start": 300.199,
    "duration": 3.201
  },
  {
    "text": "and more importantly I loved helping",
    "start": 301.96,
    "duration": 3.04
  },
  {
    "text": "students discover their potential career",
    "start": 303.4,
    "duration": 3.359
  },
  {
    "text": "path in healthcare despite the fact that",
    "start": 305.0,
    "duration": 3.96
  },
  {
    "text": "I still have much to learn in my mid-30s",
    "start": 306.759,
    "duration": 3.641
  },
  {
    "text": "this year I accepted a full-time",
    "start": 308.96,
    "duration": 2.959
  },
  {
    "text": "position as a teaching professor at a",
    "start": 310.4,
    "duration": 3.28
  },
  {
    "text": "university in Florida which has been an",
    "start": 311.919,
    "duration": 4.0
  },
  {
    "text": "amazing experience thus far my question",
    "start": 313.68,
    "duration": 4.04
  },
  {
    "text": "for you is what originally got you",
    "start": 315.919,
    "duration": 4.161
  },
  {
    "text": "motivated to teach and did your feelings",
    "start": 317.72,
    "duration": 4.0
  },
  {
    "text": "change about teaching as the years went",
    "start": 320.08,
    "duration": 4.28
  },
  {
    "text": "on like you I'm not coming from a PhD",
    "start": 321.72,
    "duration": 4.039
  },
  {
    "text": "background but rather from working in",
    "start": 324.36,
    "duration": 3.16
  },
  {
    "text": "the clinical world I fear there will",
    "start": 325.759,
    "duration": 3.081
  },
  {
    "text": "eventually be some sort of sealing",
    "start": 327.52,
    "duration": 3.399
  },
  {
    "text": "effect for me both financially and just",
    "start": 328.84,
    "duration": 3.88
  },
  {
    "text": "the idea of teaching the same thing year",
    "start": 330.919,
    "duration": 3.601
  },
  {
    "text": "after year I'm grateful for what I'm",
    "start": 332.72,
    "duration": 3.4
  },
  {
    "text": "doing and I'm enjoying what I'm doing",
    "start": 334.52,
    "duration": 3.16
  },
  {
    "text": "but I also like looking at the crystal",
    "start": 336.12,
    "duration": 3.68
  },
  {
    "text": "ball and I'm just eager to continuously",
    "start": 337.68,
    "duration": 4.12
  },
  {
    "text": "grow as both a person and a professional",
    "start": 339.8,
    "duration": 3.56
  },
  {
    "text": "which is why I love all your shows",
    "start": 341.8,
    "duration": 2.8
  },
  {
    "text": "thanks for your answer and thanks for",
    "start": 343.36,
    "duration": 2.52
  },
  {
    "text": "all that you",
    "start": 344.6,
    "duration": 3.599
  },
  {
    "text": "do wow Sean from Florida we're going to",
    "start": 345.88,
    "duration": 4.12
  },
  {
    "text": "need a bigger boat so let's bring this",
    "start": 348.199,
    "duration": 3.56
  },
  {
    "text": "back to me my whole L if I've wanted to",
    "start": 350.0,
    "duration": 3.28
  },
  {
    "text": "be a teacher I thought I would really",
    "start": 351.759,
    "duration": 4.521
  },
  {
    "text": "enjoy it and I'd be good at it and I",
    "start": 353.28,
    "duration": 4.72
  },
  {
    "text": "contemplated when I was in business",
    "start": 356.28,
    "duration": 3.359
  },
  {
    "text": "school applying to the PHD program",
    "start": 358.0,
    "duration": 3.479
  },
  {
    "text": "program and getting my PhD and pursuing",
    "start": 359.639,
    "duration": 4.12
  },
  {
    "text": "a career in Academia and a couple things",
    "start": 361.479,
    "duration": 5.081
  },
  {
    "text": "happened one my mom got very sick and I",
    "start": 363.759,
    "duration": 4.521
  },
  {
    "text": "knew that I would need to start making",
    "start": 366.56,
    "duration": 3.28
  },
  {
    "text": "money that I just didn't have the kind",
    "start": 368.28,
    "duration": 3.52
  },
  {
    "text": "of the capacity to take on another three",
    "start": 369.84,
    "duration": 3.44
  },
  {
    "text": "years a student that or not be making",
    "start": 371.8,
    "duration": 4.16
  },
  {
    "text": "money in a PhD program and also some of",
    "start": 373.28,
    "duration": 4.039
  },
  {
    "text": "it is less noble I just thought I'd",
    "start": 375.96,
    "duration": 2.4
  },
  {
    "text": "really like to get out there and start",
    "start": 377.319,
    "duration": 3.801
  },
  {
    "text": "making real bank and I didn't see how I",
    "start": 378.36,
    "duration": 4.959
  },
  {
    "text": "was going to do that as a Prof at least",
    "start": 381.12,
    "duration": 4.519
  },
  {
    "text": "initially so I went out I gave myself 10",
    "start": 383.319,
    "duration": 5.041
  },
  {
    "text": "years before I would go back to teaching",
    "start": 385.639,
    "duration": 5.641
  },
  {
    "text": "and exactly 10 years later in 2002 after",
    "start": 388.36,
    "duration": 4.72
  },
  {
    "text": "graduating from H 1992 I joined the",
    "start": 391.28,
    "duration": 2.84
  },
  {
    "text": "faculty at",
    "start": 393.08,
    "duration": 3.959
  },
  {
    "text": "NYU and uh one of the motivations for",
    "start": 394.12,
    "duration": 4.28
  },
  {
    "text": "joining was I thought I was going to be",
    "start": 397.039,
    "duration": 3.241
  },
  {
    "text": "rich and that I could leave and just go",
    "start": 398.4,
    "duration": 3.56
  },
  {
    "text": "focus on teaching and I took a job",
    "start": 400.28,
    "duration": 4.0
  },
  {
    "text": "paying $122,000 a year as an a professor",
    "start": 401.96,
    "duration": 3.0
  },
  {
    "text": "at",
    "start": 404.28,
    "duration": 3.44
  },
  {
    "text": "NYU and as you know you have your plans",
    "start": 404.96,
    "duration": 5.239
  },
  {
    "text": "that God laughs my company read envelope",
    "start": 407.72,
    "duration": 4.0
  },
  {
    "text": "to go public and on paper it was worth a",
    "start": 410.199,
    "duration": 3.881
  },
  {
    "text": "lot of money and then I wasn't when the",
    "start": 411.72,
    "duration": 5.479
  },
  {
    "text": "do bomb um implosion happened so I kind",
    "start": 414.08,
    "duration": 4.839
  },
  {
    "text": "of woke up and realized I was an adjunct",
    "start": 417.199,
    "duration": 3.72
  },
  {
    "text": "professor making $12,000 a year now",
    "start": 418.919,
    "duration": 3.441
  },
  {
    "text": "having said that I think Academia is a",
    "start": 420.919,
    "duration": 4.481
  },
  {
    "text": "wonderful career uh it's definitely a",
    "start": 422.36,
    "duration": 4.72
  },
  {
    "text": "cast system it's definitely some of the",
    "start": 425.4,
    "duration": 3.079
  },
  {
    "text": "most discriminatory business in the",
    "start": 427.08,
    "duration": 2.88
  },
  {
    "text": "world essentially the people in charge",
    "start": 428.479,
    "duration": 3.921
  },
  {
    "text": "hire their PHD buddies they write",
    "start": 429.96,
    "duration": 4.56
  },
  {
    "text": " research which is 98% of",
    "start": 432.4,
    "duration": 3.84
  },
  {
    "text": "peer-reviewed academic research is this",
    "start": 434.52,
    "duration": 3.44
  },
  {
    "text": " to give each other citations",
    "start": 436.24,
    "duration": 4.079
  },
  {
    "text": "such that they can qualify they can get",
    "start": 437.96,
    "duration": 3.959
  },
  {
    "text": "tenure which is guaranteed lifetime",
    "start": 440.319,
    "duration": 3.28
  },
  {
    "text": "employment which translates to student",
    "start": 441.919,
    "duration": 4.12
  },
  {
    "text": "debt as two-thirds of these individuals",
    "start": 443.599,
    "duration": 4.0
  },
  {
    "text": "within 20 years are totally unproductive",
    "start": 446.039,
    "duration": 4.041
  },
  {
    "text": "and overpaid and 10 years this kind of",
    "start": 447.599,
    "duration": 4.72
  },
  {
    "text": "this grift where because Galileo said",
    "start": 450.08,
    "duration": 3.64
  },
  {
    "text": "the world might be round and we thought",
    "start": 452.319,
    "duration": 3.361
  },
  {
    "text": "we need to protect academics we've",
    "start": 453.72,
    "duration": 3.36
  },
  {
    "text": "decided that the guy who came up with",
    "start": 455.68,
    "duration": 3.56
  },
  {
    "text": "gap one Accounting in 1985 deserves",
    "start": 457.08,
    "duration": 3.799
  },
  {
    "text": "lifetime employment it's just",
    "start": 459.24,
    "duration": 3.44
  },
  {
    "text": "stupid the result is that crowding at",
    "start": 460.879,
    "duration": 4.16
  },
  {
    "text": "the top of the pyramid and young",
    "start": 462.68,
    "duration": 4.239
  },
  {
    "text": "academics who are really outstanding",
    "start": 465.039,
    "duration": 4.201
  },
  {
    "text": "have trouble moving up because these",
    "start": 466.919,
    "duration": 3.641
  },
  {
    "text": "people will not",
    "start": 469.24,
    "duration": 4.56
  },
  {
    "text": "leave and most of this uh quotequote",
    "start": 470.56,
    "duration": 5.16
  },
  {
    "text": "tenure is nothing but a guild and a taxs",
    "start": 473.8,
    "duration": 3.32
  },
  {
    "text": "on young people which translates to",
    "start": 475.72,
    "duration": 3.84
  },
  {
    "text": "student debt the administrative state is",
    "start": 477.12,
    "duration": 4.799
  },
  {
    "text": "out of control at universities uh my",
    "start": 479.56,
    "duration": 4.24
  },
  {
    "text": "department shair at or one of my",
    "start": 481.919,
    "duration": 3.321
  },
  {
    "text": "department shairs in marketing was",
    "start": 483.8,
    "duration": 3.799
  },
  {
    "text": "essentially a pretty weak academic who",
    "start": 485.24,
    "duration": 4.2
  },
  {
    "text": "was a functioning or semi-functioning",
    "start": 487.599,
    "duration": 4.081
  },
  {
    "text": "alcoholic so I know let's give her an",
    "start": 489.44,
    "duration": 4.599
  },
  {
    "text": "administrative role look you're going in",
    "start": 491.68,
    "duration": 4.519
  },
  {
    "text": "as a practicing Professor here are some",
    "start": 494.039,
    "duration": 5.801
  },
  {
    "text": "tips one this is a business and the way",
    "start": 496.199,
    "duration": 5.481
  },
  {
    "text": "you increase your compensation is by",
    "start": 499.84,
    "duration": 4.0
  },
  {
    "text": "putting butts in seats you're probably",
    "start": 501.68,
    "duration": 3.04
  },
  {
    "text": "not going to do great peerreview",
    "start": 503.84,
    "duration": 2.56
  },
  {
    "text": "research I was thinking about doing peer",
    "start": 504.72,
    "duration": 3.0
  },
  {
    "text": "rreview research and then I read it I'm",
    "start": 506.4,
    "duration": 3.12
  },
  {
    "text": "like this is stupid none of this",
    "start": 507.72,
    "duration": 4.319
  },
  {
    "text": "has any relevance to anything and so I",
    "start": 509.52,
    "duration": 3.759
  },
  {
    "text": "started doing a lot of research but I",
    "start": 512.039,
    "duration": 3.041
  },
  {
    "text": "did it on the guys of a private company",
    "start": 513.279,
    "duration": 5.041
  },
  {
    "text": "called L2 and I got way more press in",
    "start": 515.08,
    "duration": 4.959
  },
  {
    "text": "kind of private sector impact than any",
    "start": 518.32,
    "duration": 3.12
  },
  {
    "text": "almost any of the peer review research",
    "start": 520.039,
    "duration": 2.601
  },
  {
    "text": "maybe the exception of some of the peer",
    "start": 521.44,
    "duration": 2.44
  },
  {
    "text": "rreview research that the finance",
    "start": 522.64,
    "duration": 3.52
  },
  {
    "text": "department does which bubbles up guys",
    "start": 523.88,
    "duration": 5.0
  },
  {
    "text": "like David yac and ASAT the motor and",
    "start": 526.16,
    "duration": 4.52
  },
  {
    "text": "his his is imp PE review research but",
    "start": 528.88,
    "duration": 4.6
  },
  {
    "text": "it's just so powerful but anyways what I",
    "start": 530.68,
    "duration": 5.48
  },
  {
    "text": "found is that the key to a currency and",
    "start": 533.48,
    "duration": 4.32
  },
  {
    "text": "there's four or five of these people",
    "start": 536.16,
    "duration": 3.08
  },
  {
    "text": "essentially at NYU Stern we have four or",
    "start": 537.8,
    "duration": 4.039
  },
  {
    "text": "five ringers and that is someone a",
    "start": 539.24,
    "duration": 3.96
  },
  {
    "text": "professor that everyone feels like they",
    "start": 541.839,
    "duration": 3.601
  },
  {
    "text": "got to take Glenn Oaken or Sonia",
    "start": 543.2,
    "duration": 5.879
  },
  {
    "text": "Marciano at NYU they are clinicals they",
    "start": 545.44,
    "duration": 5.2
  },
  {
    "text": "don't have phds they're practicing",
    "start": 549.079,
    "duration": 3.601
  },
  {
    "text": "professors but they're outstanding",
    "start": 550.64,
    "duration": 4.48
  },
  {
    "text": "teachers and because it's a business",
    "start": 552.68,
    "duration": 4.04
  },
  {
    "text": "they have to have a certain number of",
    "start": 555.12,
    "duration": 3.24
  },
  {
    "text": "classes that everyone if they take three",
    "start": 556.72,
    "duration": 2.92
  },
  {
    "text": "or four of these they feel like they got",
    "start": 558.36,
    "duration": 3.159
  },
  {
    "text": "their money's worth those people have",
    "start": 559.64,
    "duration": 3.56
  },
  {
    "text": "real currency and power I became one of",
    "start": 561.519,
    "duration": 2.801
  },
  {
    "text": "those people I became one of their",
    "start": 563.2,
    "duration": 4.44
  },
  {
    "text": "ringers and so I could put 500 butts and",
    "start": 564.32,
    "duration": 5.56
  },
  {
    "text": "seats every year which at 7,000",
    "start": 567.64,
    "duration": 4.04
  },
  {
    "text": "per class which is what we charge at NYU",
    "start": 569.88,
    "duration": 3.92
  },
  {
    "text": "Stern you're technically generating $35",
    "start": 571.68,
    "duration": 4.0
  },
  {
    "text": "million in income they're paying you a",
    "start": 573.8,
    "duration": 4.32
  },
  {
    "text": "lot less than that but you have some",
    "start": 575.68,
    "duration": 4.96
  },
  {
    "text": "currency so the key for you my friend is",
    "start": 578.12,
    "duration": 3.92
  },
  {
    "text": "just becoming outstanding at teaching",
    "start": 580.64,
    "duration": 2.8
  },
  {
    "text": "and getting more butts and",
    "start": 582.04,
    "duration": 3.88
  },
  {
    "text": "seeds uh some of the I would avoid the",
    "start": 583.44,
    "duration": 4.28
  },
  {
    "text": "administrative State you know if it's a",
    "start": 585.92,
    "duration": 3.24
  },
  {
    "text": "means of helping out fine but for the",
    "start": 587.72,
    "duration": 3.6
  },
  {
    "text": "most part I think it's mostly a waste of",
    "start": 589.16,
    "duration": 3.6
  },
  {
    "text": "time I find that most of the",
    "start": 591.32,
    "duration": 4.0
  },
  {
    "text": "administration and kind of program stuff",
    "start": 592.76,
    "duration": 5.0
  },
  {
    "text": "at on campus it's just people pushing",
    "start": 595.32,
    "duration": 4.8
  },
  {
    "text": "paper to each other and my career took",
    "start": 597.76,
    "duration": 3.88
  },
  {
    "text": "off when I decided I was going to do",
    "start": 600.12,
    "duration": 2.8
  },
  {
    "text": "nothing I was never going to spend any",
    "start": 601.64,
    "duration": 4.439
  },
  {
    "text": "time on campus unless I was teaching to",
    "start": 602.92,
    "duration": 5.039
  },
  {
    "text": "do a market check and what you do is you",
    "start": 606.079,
    "duration": 3.2
  },
  {
    "text": "quit every three to five years without",
    "start": 607.959,
    "duration": 2.721
  },
  {
    "text": "quitting every three to five years I",
    "start": 609.279,
    "duration": 2.8
  },
  {
    "text": "would interview at another University",
    "start": 610.68,
    "duration": 2.92
  },
  {
    "text": "I'd get called by a Cornell or a",
    "start": 612.079,
    "duration": 3.76
  },
  {
    "text": "wardener or Columbia I'd interview I'd",
    "start": 613.6,
    "duration": 3.919
  },
  {
    "text": "find out what the offer would be and",
    "start": 615.839,
    "duration": 3.281
  },
  {
    "text": "then I'd go to the dean or my department",
    "start": 617.519,
    "duration": 3.201
  },
  {
    "text": "chair and say I don't want to leave I'd",
    "start": 619.12,
    "duration": 4.399
  },
  {
    "text": "be transparent but this is my current",
    "start": 620.72,
    "duration": 4.28
  },
  {
    "text": "value in the marketplace I knew I had",
    "start": 623.519,
    "duration": 3.601
  },
  {
    "text": "some currency because fortunately for me",
    "start": 625.0,
    "duration": 4.04
  },
  {
    "text": "the marketing department was not very",
    "start": 627.12,
    "duration": 2.959
  },
  {
    "text": "strong",
    "start": 629.04,
    "duration": 3.88
  },
  {
    "text": "in terms of in room teaching and they",
    "start": 630.079,
    "duration": 5.801
  },
  {
    "text": "would match it and so you know you got",
    "start": 632.92,
    "duration": 5.4
  },
  {
    "text": "to recognize that the leadership of",
    "start": 635.88,
    "duration": 4.68
  },
  {
    "text": "universities generally sees adjuncts and",
    "start": 638.32,
    "duration": 5.12
  },
  {
    "text": "clinicals as sort of I don't know like",
    "start": 640.56,
    "duration": 4.279
  },
  {
    "text": "Russian soldiers that they just kind of",
    "start": 643.44,
    "duration": 3.28
  },
  {
    "text": "throw into the meat grinder and that is",
    "start": 644.839,
    "duration": 3.44
  },
  {
    "text": "oh it's your calling you don't actually",
    "start": 646.72,
    "duration": 3.44
  },
  {
    "text": "need health benefits or money we save",
    "start": 648.279,
    "duration": 4.321
  },
  {
    "text": "that for the tenure faculty so you have",
    "start": 650.16,
    "duration": 4.28
  },
  {
    "text": "to create your own currency through",
    "start": 652.6,
    "duration": 3.039
  },
  {
    "text": "butts and seats and then you have to",
    "start": 654.44,
    "duration": 3.32
  },
  {
    "text": "leverage it by occasionally interviewing",
    "start": 655.639,
    "duration": 4.121
  },
  {
    "text": "with another University that's kind of",
    "start": 657.76,
    "duration": 3.92
  },
  {
    "text": "the politics of the how the sausage is",
    "start": 659.76,
    "duration": 4.4
  },
  {
    "text": "made having said that you generally are",
    "start": 661.68,
    "duration": 4.399
  },
  {
    "text": "in an environment where people are not",
    "start": 664.16,
    "duration": 4.28
  },
  {
    "text": " they they fight over every",
    "start": 666.079,
    "duration": 3.76
  },
  {
    "text": "little thing because they're so little",
    "start": 668.44,
    "duration": 3.0
  },
  {
    "text": "at risk or they're so little to be",
    "start": 669.839,
    "duration": 3.521
  },
  {
    "text": "gained but generally speaking the people",
    "start": 671.44,
    "duration": 5.0
  },
  {
    "text": "are pretty nice the best academics are",
    "start": 673.36,
    "duration": 4.36
  },
  {
    "text": "some of the most inspiring people you",
    "start": 676.44,
    "duration": 3.12
  },
  {
    "text": "ever run across being on campus is",
    "start": 677.72,
    "duration": 3.52
  },
  {
    "text": "incredibly inspiring you do feel as if",
    "start": 679.56,
    "duration": 3.16
  },
  {
    "text": "you're adding value being around young",
    "start": 681.24,
    "duration": 4.88
  },
  {
    "text": "people is just incredibly I don't know",
    "start": 682.72,
    "duration": 6.04
  },
  {
    "text": "invigorating but let me finish where I",
    "start": 686.12,
    "duration": 4.92
  },
  {
    "text": "started lot there lot there lot of",
    "start": 688.76,
    "duration": 4.4
  },
  {
    "text": "trauma a lot of PTSD but a lot of reward",
    "start": 691.04,
    "duration": 4.52
  },
  {
    "text": "too thanks for the question",
    "start": 693.16,
    "duration": 4.64
  },
  {
    "text": "Sean we have one quick break before our",
    "start": 695.56,
    "duration": 5.32
  },
  {
    "text": "final question stay with",
    "start": 697.8,
    "duration": 3.08
  },
  {
    "text": "us welcome back question number three hi",
    "start": 704.04,
    "duration": 5.479
  },
  {
    "text": "Scott this is Duncan from Tokyo Japan",
    "start": 707.24,
    "duration": 4.279
  },
  {
    "text": "I'm 40 years old originally from Canada",
    "start": 709.519,
    "duration": 4.481
  },
  {
    "text": "and work in big Tech now Scott you've",
    "start": 711.519,
    "duration": 4.961
  },
  {
    "text": "been hyper successful throughout your",
    "start": 714.0,
    "duration": 3.8
  },
  {
    "text": "career and you have many different",
    "start": 716.48,
    "duration": 3.0
  },
  {
    "text": "Endeavors going on at the same time",
    "start": 717.8,
    "duration": 4.039
  },
  {
    "text": "which I assume requires a lot of energy",
    "start": 719.48,
    "duration": 3.919
  },
  {
    "text": "I just love to hear your thoughts on how",
    "start": 721.839,
    "duration": 4.521
  },
  {
    "text": "to best create and manage energy and if",
    "start": 723.399,
    "duration": 4.801
  },
  {
    "text": "laziness happens to be a bit of a",
    "start": 726.36,
    "duration": 3.36
  },
  {
    "text": "challenge for you it sometimes what",
    "start": 728.2,
    "duration": 3.8
  },
  {
    "text": "tactics you have to battle it thank you",
    "start": 729.72,
    "duration": 4.76
  },
  {
    "text": "so much and I hope to hear back from you",
    "start": 732.0,
    "duration": 4.519
  },
  {
    "text": "thanks for the question um this really",
    "start": 734.48,
    "duration": 4.2
  },
  {
    "text": "resonates with me Duncan because I am",
    "start": 736.519,
    "duration": 6.0
  },
  {
    "text": "fundamentally a lazy person and uh",
    "start": 738.68,
    "duration": 5.2
  },
  {
    "text": "people are under the impression that I'm",
    "start": 742.519,
    "duration": 3.041
  },
  {
    "text": "working all the time because of the",
    "start": 743.88,
    "duration": 3.6
  },
  {
    "text": "content we put out they think it's me",
    "start": 745.56,
    "duration": 5.56
  },
  {
    "text": "and you know upload in videos to YouTube",
    "start": 747.48,
    "duration": 5.799
  },
  {
    "text": "and drawing sketching out these charts",
    "start": 751.12,
    "duration": 4.2
  },
  {
    "text": "on a napkin you know they're like it's",
    "start": 753.279,
    "duration": 3.56
  },
  {
    "text": "amazing how much content you put out",
    "start": 755.32,
    "duration": 3.84
  },
  {
    "text": "well now it's amazing how much credit I",
    "start": 756.839,
    "duration": 5.041
  },
  {
    "text": "get for the content we put out a couple",
    "start": 759.16,
    "duration": 4.64
  },
  {
    "text": "things as it relates to laziness",
    "start": 761.88,
    "duration": 5.24
  },
  {
    "text": "Investment Banking and crew were both",
    "start": 763.8,
    "duration": 5.92
  },
  {
    "text": "really important for me because without",
    "start": 767.12,
    "duration": 4.839
  },
  {
    "text": "a rot schedule without having to drag my",
    "start": 769.72,
    "duration": 4.76
  },
  {
    "text": "ass out of bed at 5:00 a.m. or I'd be",
    "start": 771.959,
    "duration": 4.56
  },
  {
    "text": "letting seven other men out down in the",
    "start": 774.48,
    "duration": 3.88
  },
  {
    "text": "boat and my coach would kick me off the",
    "start": 776.519,
    "duration": 3.56
  },
  {
    "text": "team I just would have never gotten up",
    "start": 778.36,
    "duration": 4.4
  },
  {
    "text": "at 5:00 a.m. without the pressure and",
    "start": 780.079,
    "duration": 4.88
  },
  {
    "text": "the routinization and the scheduling and",
    "start": 782.76,
    "duration": 3.96
  },
  {
    "text": "and the demands of investment banking I",
    "start": 784.959,
    "duration": 3.841
  },
  {
    "text": "just never would have worked that hard",
    "start": 786.72,
    "duration": 4.919
  },
  {
    "text": "so I've tried to put myself in a context",
    "start": 788.8,
    "duration": 5.479
  },
  {
    "text": "where I had no choice and also I think",
    "start": 791.639,
    "duration": 4.44
  },
  {
    "text": "deadlines are really important for a",
    "start": 794.279,
    "duration": 5.12
  },
  {
    "text": "lazy person my publisher you know they I",
    "start": 796.079,
    "duration": 5.2
  },
  {
    "text": "don't know they got 50 70 80% of my book",
    "start": 799.399,
    "duration": 3.761
  },
  {
    "text": "revenues and really all they do is set",
    "start": 801.279,
    "duration": 3.321
  },
  {
    "text": "deadlines and but those are really",
    "start": 803.16,
    "duration": 2.84
  },
  {
    "text": "important for me because without them",
    "start": 804.6,
    "duration": 2.76
  },
  {
    "text": "I'm not sure I think I'd put out a book",
    "start": 806.0,
    "duration": 4.16
  },
  {
    "text": "every 5 years instead of every 18 months",
    "start": 807.36,
    "duration": 5.64
  },
  {
    "text": "so try and find a context or platforms",
    "start": 810.16,
    "duration": 4.76
  },
  {
    "text": "that just quite frankly manage you and",
    "start": 813.0,
    "duration": 5.88
  },
  {
    "text": "impose deadlines on you um I try to",
    "start": 814.92,
    "duration": 6.96
  },
  {
    "text": "reduce the amount of time in between the",
    "start": 818.88,
    "duration": 4.72
  },
  {
    "text": "decision to do something and doing it",
    "start": 821.88,
    "duration": 3.84
  },
  {
    "text": "I'm trying to be more Reckless oh I",
    "start": 823.6,
    "duration": 3.72
  },
  {
    "text": "should work out okay start putting on",
    "start": 825.72,
    "duration": 4.28
  },
  {
    "text": "your gym clothes don't think about it I",
    "start": 827.32,
    "duration": 4.319
  },
  {
    "text": "get you know this is a position of",
    "start": 830.0,
    "duration": 2.8
  },
  {
    "text": "privilege but one of the reasons I have",
    "start": 831.639,
    "duration": 2.801
  },
  {
    "text": "a trainers not because they do anything",
    "start": 832.8,
    "duration": 4.0
  },
  {
    "text": "I don't know but if there's a guy in my",
    "start": 834.44,
    "duration": 4.68
  },
  {
    "text": "backyard at 8: a.m. on a Tuesday morning",
    "start": 836.8,
    "duration": 3.64
  },
  {
    "text": "I got to get out there sometimes I wait",
    "start": 839.12,
    "duration": 2.92
  },
  {
    "text": "till 8:10 cuz I'm so lazy and",
    "start": 840.44,
    "duration": 2.759
  },
  {
    "text": "I'll just pop my head out and say hey",
    "start": 842.04,
    "duration": 2.88
  },
  {
    "text": "Sean I'll be out in 10 minutes but",
    "start": 843.199,
    "duration": 3.241
  },
  {
    "text": "eventually I get out there whereas if I",
    "start": 844.92,
    "duration": 3.08
  },
  {
    "text": "was allowed to sleep in till 9:00 and",
    "start": 846.44,
    "duration": 3.079
  },
  {
    "text": "then have some coffee and doodle around",
    "start": 848.0,
    "duration": 3.12
  },
  {
    "text": "and I'm like oh no the podcast is at 10",
    "start": 849.519,
    "duration": 4.44
  },
  {
    "text": "too bad I can't work out so scheduling",
    "start": 851.12,
    "duration": 6.44
  },
  {
    "text": "forcing routine deadlines super",
    "start": 853.959,
    "duration": 6.961
  },
  {
    "text": "important for a lazy person in addition",
    "start": 857.56,
    "duration": 5.839
  },
  {
    "text": "and also this notion get rid of the time",
    "start": 860.92,
    "duration": 4.88
  },
  {
    "text": "in between the decision and doing oh I",
    "start": 863.399,
    "duration": 4.081
  },
  {
    "text": "should really call someone or I I need",
    "start": 865.8,
    "duration": 3.44
  },
  {
    "text": "to return this and just start writing it",
    "start": 867.48,
    "duration": 3.68
  },
  {
    "text": "I need I'm terrible I get so many emails",
    "start": 869.24,
    "duration": 3.159
  },
  {
    "text": "from people I want to respond to and I",
    "start": 871.16,
    "duration": 3.16
  },
  {
    "text": "think I'll do it later now what I need",
    "start": 872.399,
    "duration": 3.721
  },
  {
    "text": "to do and I don't do this all the time I",
    "start": 874.32,
    "duration": 3.36
  },
  {
    "text": "need to get back to this person start",
    "start": 876.12,
    "duration": 3.6
  },
  {
    "text": "getting back to them now there's nothing",
    "start": 877.68,
    "duration": 3.399
  },
  {
    "text": "like now and even if it's a little",
    "start": 879.72,
    "duration": 4.4
  },
  {
    "text": "reckless just oh I'd like to you know I",
    "start": 881.079,
    "duration": 4.961
  },
  {
    "text": "need to take these supplement wear the",
    "start": 884.12,
    "duration": 4.56
  },
  {
    "text": " pills wear the don't plan",
    "start": 886.04,
    "duration": 4.12
  },
  {
    "text": "just the inclination try and get into",
    "start": 888.68,
    "duration": 2.88
  },
  {
    "text": "the practice of what I'm doing as soon",
    "start": 890.16,
    "duration": 2.56
  },
  {
    "text": "as I think I need to do something okay",
    "start": 891.56,
    "duration": 2.76
  },
  {
    "text": "start doing it don't don't think about",
    "start": 892.72,
    "duration": 3.919
  },
  {
    "text": "it don't plan it just start doing it and",
    "start": 894.32,
    "duration": 6.68
  },
  {
    "text": "get on it uh otherwise I just can't get",
    "start": 896.639,
    "duration": 6.961
  },
  {
    "text": "over I did I was in Barcelona yesterday",
    "start": 901.0,
    "duration": 4.32
  },
  {
    "text": "I had all these plans for walking around",
    "start": 903.6,
    "duration": 4.4
  },
  {
    "text": "doing some videos writing proofing",
    "start": 905.32,
    "duration": 4.519
  },
  {
    "text": "editing a chapter and writing a book on",
    "start": 908.0,
    "duration": 5.16
  },
  {
    "text": "masculinity I did nothing by the",
    "start": 909.839,
    "duration": 4.961
  },
  {
    "text": "time I was at the noou hotel by the time",
    "start": 913.16,
    "duration": 4.599
  },
  {
    "text": "I went out and had my weird Sushi launch",
    "start": 914.8,
    "duration": 5.36
  },
  {
    "text": "and went online and watched Tik Tok for",
    "start": 917.759,
    "duration": 4.52
  },
  {
    "text": "two hours I literally wasted I didn't",
    "start": 920.16,
    "duration": 3.96
  },
  {
    "text": "even walk around one of what is one of",
    "start": 922.279,
    "duration": 3.24
  },
  {
    "text": "the most impressive cities in the world",
    "start": 924.12,
    "duration": 5.079
  },
  {
    "text": "I did goddamn nothing nothing um because",
    "start": 925.519,
    "duration": 5.361
  },
  {
    "text": "I wasn't scheduled and I didn't have",
    "start": 929.199,
    "duration": 3.76
  },
  {
    "text": "things going on today quite frankly I am",
    "start": 930.88,
    "duration": 4.8
  },
  {
    "text": "booked so solid my assistant and my team",
    "start": 932.959,
    "duration": 4.68
  },
  {
    "text": "has me doing so much of this pods",
    "start": 935.68,
    "duration": 3.519
  },
  {
    "text": "I'm hosting a l and you know what I need",
    "start": 937.639,
    "duration": 4.44
  },
  {
    "text": "it I need that scheduling so try and put",
    "start": 939.199,
    "duration": 3.961
  },
  {
    "text": "yourself in a position where you have",
    "start": 942.079,
    "duration": 2.68
  },
  {
    "text": "deadlines and schedules imposed on each",
    "start": 943.16,
    "duration": 3.56
  },
  {
    "text": "other get rid of the gap between I need",
    "start": 944.759,
    "duration": 5.0
  },
  {
    "text": "to do this and actually doing it also in",
    "start": 946.72,
    "duration": 5.32
  },
  {
    "text": "this is a a position of privilege",
    "start": 949.759,
    "duration": 4.601
  },
  {
    "text": "greatness is in the agency of others",
    "start": 952.04,
    "duration": 3.599
  },
  {
    "text": "I've always realized that if it's just",
    "start": 954.36,
    "duration": 2.959
  },
  {
    "text": "me as a so proprietor I'm not going to",
    "start": 955.639,
    "duration": 4.081
  },
  {
    "text": "put out that much because I'm lazy",
    "start": 957.319,
    "duration": 4.08
  },
  {
    "text": "uh but what I've done is I've tried to",
    "start": 959.72,
    "duration": 3.64
  },
  {
    "text": "figure out what am I really good at that",
    "start": 961.399,
    "duration": 4.041
  },
  {
    "text": "no one else can do and I Outsource",
    "start": 963.36,
    "duration": 4.0
  },
  {
    "text": "everything else now that requires some",
    "start": 965.44,
    "duration": 4.28
  },
  {
    "text": "capital I have producers who write up",
    "start": 967.36,
    "duration": 4.399
  },
  {
    "text": "scripts for me I have someone helping me",
    "start": 969.72,
    "duration": 3.88
  },
  {
    "text": "with my book I have someone who does all",
    "start": 971.759,
    "duration": 4.2
  },
  {
    "text": "our charts I have someone who manages",
    "start": 973.6,
    "duration": 3.799
  },
  {
    "text": "the business the hiring and firing I",
    "start": 975.959,
    "duration": 3.841
  },
  {
    "text": "have a CFO I just I have a personal",
    "start": 977.399,
    "duration": 4.12
  },
  {
    "text": "assistant when I say personal I'm going",
    "start": 979.8,
    "duration": 2.92
  },
  {
    "text": "to New York tonight she's going to make",
    "start": 981.519,
    "duration": 2.921
  },
  {
    "text": "sure I have granola and milk in my",
    "start": 982.72,
    "duration": 3.08
  },
  {
    "text": "refrigerator so said I don't have to go",
    "start": 984.44,
    "duration": 2.519
  },
  {
    "text": "out and get it obviously I have someone",
    "start": 985.8,
    "duration": 3.32
  },
  {
    "text": "who cleans my home someone who trains me",
    "start": 986.959,
    "duration": 3.841
  },
  {
    "text": "I'm a big believer in comparative",
    "start": 989.12,
    "duration": 3.079
  },
  {
    "text": "advantage and that is once you have a",
    "start": 990.8,
    "duration": 3.32
  },
  {
    "text": "little bit of money start thinking how",
    "start": 992.199,
    "duration": 4.08
  },
  {
    "text": "do I save time and some of that might",
    "start": 994.12,
    "duration": 4.68
  },
  {
    "text": "just be for you just to be lazy but to",
    "start": 996.279,
    "duration": 4.04
  },
  {
    "text": "free you up on the things you're good at",
    "start": 998.8,
    "duration": 3.36
  },
  {
    "text": "let's summarize put yourself in a",
    "start": 1000.319,
    "duration": 3.841
  },
  {
    "text": "situation where you have imposed",
    "start": 1002.16,
    "duration": 5.0
  },
  {
    "text": "deadlines a schedule try to eliminate",
    "start": 1004.16,
    "duration": 4.64
  },
  {
    "text": "the time or reduce the time between I",
    "start": 1007.16,
    "duration": 3.84
  },
  {
    "text": "need to and actually just starting on it",
    "start": 1008.8,
    "duration": 3.92
  },
  {
    "text": "just start oh I need to write a chapter",
    "start": 1011.0,
    "duration": 3.92
  },
  {
    "text": "just okay throw up in the laptop",
    "start": 1012.72,
    "duration": 4.239
  },
  {
    "text": "and start writing even if it's",
    "start": 1014.92,
    "duration": 3.44
  },
  {
    "text": "beauty is in the edit by the way when it",
    "start": 1016.959,
    "duration": 2.721
  },
  {
    "text": "comes to writing",
    "start": 1018.36,
    "duration": 3.719
  },
  {
    "text": "and finally as soon as you can as soon",
    "start": 1019.68,
    "duration": 3.76
  },
  {
    "text": "as you have the resources start",
    "start": 1022.079,
    "duration": 3.201
  },
  {
    "text": "Outsourcing the stuff that you're not",
    "start": 1023.44,
    "duration": 5.16
  },
  {
    "text": "good at or that doesn't in any way um",
    "start": 1025.28,
    "duration": 6.519
  },
  {
    "text": "leverage your unique skills but again I",
    "start": 1028.6,
    "duration": 6.28
  },
  {
    "text": "think laziness is underappreciated I",
    "start": 1031.799,
    "duration": 4.28
  },
  {
    "text": "think there's a lot of us out there that",
    "start": 1034.88,
    "duration": 2.84
  },
  {
    "text": "are fundamentally lazy people you just",
    "start": 1036.079,
    "duration": 3.84
  },
  {
    "text": "have to recognize your weakness and put",
    "start": 1037.72,
    "duration": 4.079
  },
  {
    "text": "in place the infrastructure such that",
    "start": 1039.919,
    "duration": 5.721
  },
  {
    "text": "you can do a workaround thanks for the",
    "start": 1041.799,
    "duration": 6.04
  },
  {
    "text": "question that's all for this episode if",
    "start": 1045.64,
    "duration": 3.56
  },
  {
    "text": "you'd like to submit a question question",
    "start": 1047.839,
    "duration": 2.96
  },
  {
    "text": "please email a voice recording to office",
    "start": 1049.2,
    "duration": 3.92
  },
  {
    "text": "hours atpr media.com again that's office",
    "start": 1050.799,
    "duration": 6.161
  },
  {
    "text": "hours atpr media.com",
    "start": 1053.12,
    "duration": 3.84
  }
]